dequindre/__init__.py
dequindre/commons.py
dequindre/exceptions.py
dequindre-0.10.0.dist-info/LICENSE
dequindre-0.10.0.dist-info/METADATA
dequindre-0.10.0.dist-info/WHEEL
dequindre-0.10.0.dist-info/top_level.txt
dequindre-0.10.0.dist-info/RECORD
