Metadata-Version: 2.1
Name: dequindre
Version: 0.10.0
Summary: Dequindre /de-KWIN-der/ (n.): A minimalist scheduler.
Home-page: https://github.com/vogt4nick/dequindre
Author: Nick Vogt
Author-email: vogt4nick@gmail.com
License: UNKNOWN
Platform: UNKNOWN
Classifier: Development Status :: 4 - Beta
Classifier: Programming Language :: Python :: 2.7
Classifier: Programming Language :: Python :: 3.4
Classifier: Programming Language :: Python :: 3.5
Classifier: Programming Language :: Python :: 3.6
Classifier: Programming Language :: Python :: 3.7
Classifier: Topic :: Software Development :: Libraries :: Python Modules
Classifier: License :: OSI Approved :: MIT License
Classifier: Operating System :: OS Independent
Classifier: Intended Audience :: Developers
Classifier: Intended Audience :: Education
